desktop_stickers/__init__.py
desktop_stickers/cli.py
desktop_stickers/main.py
dster-1.0.0.dist-info/licenses/LICENSE
dster-1.0.0.dist-info/METADATA
dster-1.0.0.dist-info/WHEEL
dster-1.0.0.dist-info/entry_points.txt
dster-1.0.0.dist-info/top_level.txt
dster-1.0.0.dist-info/RECORD
