Metadata-Version: 2.4
Name: dster
Version: 1.0.0
Summary: 一个在Windows桌面上显示动态卡通贴纸的Python程序
Home-page: https://github.com/ylicen/desktop-stickers
Author: ylicen
Author-email: sokllmiller@gmail.com
Project-URL: Bug Reports, https://github.com/yourusername/desktop-stickers/issues
Project-URL: Source, https://github.com/yourusername/desktop-stickers
Keywords: desktop,stickers,pygame,windows,animation,cartoon
Classifier: Development Status :: 4 - Beta
Classifier: Intended Audience :: End Users/Desktop
Classifier: License :: OSI Approved :: MIT License
Classifier: Operating System :: Microsoft :: Windows
Classifier: Programming Language :: Python :: 3
Classifier: Programming Language :: Python :: 3.7
Classifier: Programming Language :: Python :: 3.8
Classifier: Programming Language :: Python :: 3.9
Classifier: Programming Language :: Python :: 3.10
Classifier: Programming Language :: Python :: 3.11
Classifier: Topic :: Games/Entertainment
Classifier: Topic :: Multimedia :: Graphics
Classifier: Topic :: Desktop Environment
Requires-Python: >=3.7
License-File: LICENSE
Requires-Dist: pygame>=2.0.0
Provides-Extra: dev
Requires-Dist: build; extra == "dev"
Requires-Dist: twine; extra == "dev"
Requires-Dist: wheel; extra == "dev"
Dynamic: author
Dynamic: author-email
Dynamic: classifier
Dynamic: description
Dynamic: description-content-type
Dynamic: home-page
Dynamic: keywords
Dynamic: license-file
Dynamic: project-url
Dynamic: provides-extra
Dynamic: requires-dist
Dynamic: requires-python
Dynamic: summary
